docs/conf.py
docs/_add_docs/api_doc/conf.py
docs/_add_docs/full_doc/conf.py
docs/_add_docs/manual_doc/conf.py
env/bin/activate_this.py
env/bin/rst2html.py
env/bin/rst2html4.py
env/bin/rst2html5.py
env/bin/rst2latex.py
env/bin/rst2man.py
env/bin/rst2odt.py
env/bin/rst2odt_prepstyles.py
env/bin/rst2pseudoxml.py
env/bin/rst2s5.py
env/bin/rst2xetex.py
env/bin/rst2xml.py
env/bin/rstpep2html.py
examples/example_direct_data.py
examples/example_direct_single_data.py
examples/example_file_reference.py
examples/example_global_config_file.py
examples/example_metric_config_file.py
examples/example_new_metric.py
examples/example_simple_metric.py
examples/specific_examples/AbsoluteDetectionDistance_example.py
examples/specific_examples/AffiliationbasedFScore_example.py
examples/specific_examples/AverageDetectionCount_example.py
examples/specific_examples/BalancedPointadjustedFScore_example.py
examples/specific_examples/CompositeFScore_example.py
examples/specific_examples/DelayThresholdedPointadjustedFScore_example.py
examples/specific_examples/DetectionAccuracyInRange_example.py
examples/specific_examples/DiceCoefficient_example.py
examples/specific_examples/EarlyDetection_example.py
examples/specific_examples/EnhancedTimeseriesAwareFScore_example.py
examples/specific_examples/LatencySparsityawareFScore_example.py
examples/specific_examples/MeanTimeToDetect_example.py
examples/specific_examples/NabScore_example.py
examples/specific_examples/NormalizedAffiliationbasedFScore_example.py
examples/specific_examples/PateFScore_example.py
examples/specific_examples/Pate_example.py
examples/specific_examples/PointadjustedAtKFScore_example.py
examples/specific_examples/PointadjustedAucPr_example.py
examples/specific_examples/PointadjustedAucRoc_example.py
examples/specific_examples/PointadjustedFScoreAtKL_example.py
examples/specific_examples/PointadjustedFScore_example.py
examples/specific_examples/PointwiseFScore_example.py
examples/specific_examples/RangebasedFScore_example.py
tsadmetrics-1.0.8.dist-info/METADATA
tsadmetrics-1.0.8.dist-info/WHEEL
tsadmetrics-1.0.8.dist-info/top_level.txt
tsadmetrics-1.0.8.dist-info/RECORD
