Metadata-Version: 2.1
Name: tsadmetrics
Version: 1.0.8
Summary: Librería para evaluación de detección de anomalías en series temporales
Author-email: Pedro Rafael Velasco Priego <i12veprp@uco.es>, Amelia Zafra Gómez <azafra@uco.es>
Requires-Python: >=3.8
Requires-Dist: numpy==1.24.4
Requires-Dist: pandas==2.0.3
Requires-Dist: PATE==0.1.1
Requires-Dist: PyYAML==6.0.2
Provides-Extra: dev
Requires-Dist: pytest==8.3.5; extra == "dev"
Requires-Dist: iniconfig==2.1.0; extra == "dev"
Requires-Dist: pluggy==1.5.0; extra == "dev"
Requires-Dist: tomli==2.2.1; extra == "dev"
Requires-Dist: exceptiongroup==1.3.0; extra == "dev"
Requires-Dist: ipython>=7.0; extra == "dev"
Requires-Dist: sphinx; extra == "dev"
Requires-Dist: sphinx-rtd-theme; extra == "dev"
Requires-Dist: numpydoc; extra == "dev"
Requires-Dist: myst-parser; extra == "dev"
